{
  "page": 1,
  "value": [
    {
      "path": "_news/2021-08-07-general-availability-azure-expressroute-global-reach-2-new-locations.md",
      "title": "General availability: Azure ExpressRoute Global Reach: 2 new locations",
      "excerpt": "ExpressRoute Global Reach allows you to link ExpressRoute circuits in different locations together to make a private network between your on-premises networks.",
      "sourceUrl": null,
      "webUrl": "https://azure.microsoft.com/en-us/updates/general-availability-azure-expressroute-global-reach-2-new-locations/",
      "originalUrl": "https://azure.microsoft.com/en-us/updates/general-availability-azure-expressroute-global-reach-2-new-locations/",
      "featuredContent": null,
      "highlight": null,
      "heat": 127,
      "tags": null,
      "images": null,
      "content": "\r\n",
      "type": "article",
      "ampWebUrl": null,
      "cdnAmpWebUrl": null,
      "publishedDateTime": "2021-08-06T17:21:05-07:00",
      "updatedDateTime": null,
      "provider": {
        "name": "Microsoft",
        "domain": "microsoft.com",
        "images": [
          {
            "url": "https://everyday-cc.github.io/azure/assets/images/organizations/microsoft.com-50x50.jpg",
            "width": 50,
            "height": 50,
            "title": null,
            "attribution": null,
            "isCached": false
          }
        ],
        "publishers": null,
        "authors": null
      },
      "locale": "en-us",
      "categories": [
        "news"
      ],
      "topics": [
        "Azure"
      ]
    },
    {
      "path": "_news/2021-08-06-availability-zone-support-for-azure-automation-is-coming-soon.md",
      "title": "Availability Zone support for Azure Automation is coming soon",
      "excerpt": "Achieve higher reliability and resiliency through Availability Zones in Azure Automation.",
      "sourceUrl": null,
      "webUrl": "https://azure.microsoft.com/en-us/updates/availability-zones-azure-automation-coming-soon/",
      "originalUrl": "https://azure.microsoft.com/en-us/updates/availability-zones-azure-automation-coming-soon/",
      "featuredContent": null,
      "highlight": null,
      "heat": 127,
      "tags": null,
      "images": null,
      "content": "\r\n",
      "type": "article",
      "ampWebUrl": null,
      "cdnAmpWebUrl": null,
      "publishedDateTime": "2021-08-06T09:00:07-07:00",
      "updatedDateTime": null,
      "provider": {
        "name": "Microsoft",
        "domain": "microsoft.com",
        "images": [
          {
            "url": "https://everyday-cc.github.io/azure/assets/images/organizations/microsoft.com-50x50.jpg",
            "width": 50,
            "height": 50,
            "title": null,
            "attribution": null,
            "isCached": false
          }
        ],
        "publishers": null,
        "authors": null
      },
      "locale": "en-us",
      "categories": [
        "news"
      ],
      "topics": [
        "Azure"
      ]
    },
    {
      "path": "_news/2021-08-06-carepoint-health-achieves-operational-simplicity-with-rubrik-cloud-data-management-and-microsoft-azure.md",
      "title": "CarePoint Health Achieves Operational Simplicity with Rubrik Cloud Data Management and Microsoft Azure",
      "excerpt": "CarePoint Health combines the resources of three area hospitals, Bayonne Medical Center, Christ Hospital in Jersey City, and Hoboken University Medical Center, to provide 360 degree coordinated care delivered by the area’s most dedicated doctors, nurses ...",
      "sourceUrl": null,
      "webUrl": "https://www.infoworld.com/resources/222727/carepoint-health-achieves-operational-simplicity-with-rubrik-cloud-data-management-and-microsoft-azu",
      "originalUrl": "https://www.infoworld.com/resources/222727/carepoint-health-achieves-operational-simplicity-with-rubrik-cloud-data-management-and-microsoft-azu",
      "featuredContent": null,
      "highlight": null,
      "heat": 101,
      "tags": null,
      "images": [
        {
          "url": "https://idge.staticworld.net/ifw/IFW_logo_social_300x300.png",
          "width": 300,
          "height": 300,
          "title": null,
          "attribution": null,
          "isCached": true
        }
      ],
      "content": "\r\n",
      "type": "article",
      "ampWebUrl": null,
      "cdnAmpWebUrl": null,
      "publishedDateTime": "2021-08-06T08:54:00-07:00",
      "updatedDateTime": null,
      "provider": {
        "name": "InfoWorld",
        "domain": "infoworld.com",
        "images": [
          {
            "url": "https://everyday-cc.github.io/azure/assets/images/organizations/infoworld.com-50x50.jpg",
            "width": 50,
            "height": 50,
            "title": null,
            "attribution": null,
            "isCached": false
          }
        ],
        "publishers": null,
        "authors": null
      },
      "locale": "en-us",
      "categories": [
        "news"
      ],
      "topics": [
        "Azure"
      ]
    },
    {
      "path": "_news/2021-08-04-private-dns-zone-integration-for-azure-database-for-postgresql-flexible-server-in-public-preview.md",
      "title": "Private DNS zone integration for Azure Database for PostgreSQL – Flexible Server in public preview",
      "excerpt": "Private DNS zone integration is now available for Flexible Server on Azure Database for PostgreSQL, a managed service running the open source Postgres database.",
      "sourceUrl": null,
      "webUrl": "https://azure.microsoft.com/en-us/updates/private-dns-zone-integration-for-azure-database-for-postgresql-flexible-server-in-public-preview/",
      "originalUrl": "https://azure.microsoft.com/en-us/updates/private-dns-zone-integration-for-azure-database-for-postgresql-flexible-server-in-public-preview/",
      "featuredContent": null,
      "highlight": null,
      "heat": 739,
      "tags": null,
      "images": null,
      "content": "\r\n",
      "type": "article",
      "ampWebUrl": null,
      "cdnAmpWebUrl": null,
      "publishedDateTime": "2021-08-04T09:00:05-07:00",
      "updatedDateTime": null,
      "provider": {
        "name": "Microsoft",
        "domain": "microsoft.com",
        "images": [
          {
            "url": "https://everyday-cc.github.io/azure/assets/images/organizations/microsoft.com-50x50.jpg",
            "width": 50,
            "height": 50,
            "title": null,
            "attribution": null,
            "isCached": false
          }
        ],
        "publishers": null,
        "authors": null
      },
      "locale": "en-us",
      "categories": [
        "news"
      ],
      "topics": [
        "Azure",
        "Databases",
        "Networking",
        "Integration"
      ]
    },
    {
      "path": "_news/2021-07-29-immutable-storage-with-versioning-for-blob-storage-is-now-in-public-preview.md",
      "title": "Immutable storage with versioning for Blob Storage is now in public preview",
      "excerpt": "Set time-based policies or legal holds on data so that the data becomes non-erasable and non-modifiable and protect all versions of a blob.",
      "sourceUrl": null,
      "webUrl": "https://azure.microsoft.com/en-us/updates/immutable-storage-with-versioning-for-blob-storage-is-now-in-public-preview/",
      "originalUrl": "https://azure.microsoft.com/en-us/updates/immutable-storage-with-versioning-for-blob-storage-is-now-in-public-preview/",
      "featuredContent": null,
      "highlight": null,
      "heat": 122,
      "tags": null,
      "images": null,
      "content": "\r\n",
      "type": "article",
      "ampWebUrl": null,
      "cdnAmpWebUrl": null,
      "publishedDateTime": "2021-07-29T10:00:36-07:00",
      "updatedDateTime": null,
      "provider": {
        "name": "Microsoft",
        "domain": "microsoft.com",
        "images": [
          {
            "url": "https://everyday-cc.github.io/azure/assets/images/organizations/microsoft.com-50x50.jpg",
            "width": 50,
            "height": 50,
            "title": null,
            "attribution": null,
            "isCached": false
          }
        ],
        "publishers": null,
        "authors": null
      },
      "locale": "en-us",
      "categories": [
        "news"
      ],
      "topics": [
        "Azure",
        "Storage"
      ]
    },
    {
      "path": "_news/2021-07-29-advancing-your-financial-services-strategy-with-azure-sustainability.md",
      "title": "Advancing your financial services strategy with Azure sustainability",
      "excerpt": "Given the growing importance of sustainability, this article will address how sustainability strategies can be utilized as a catalyst for business growth, particularly in the financial services industry, and how Microsoft Azure is uniquely positioned to help our customers achieve these goals.",
      "sourceUrl": null,
      "webUrl": "https://azure.microsoft.com/blog/advancing-your-financial-services-strategy-with-azure-sustainability/",
      "originalUrl": "https://azure.microsoft.com/blog/advancing-your-financial-services-strategy-with-azure-sustainability/",
      "featuredContent": null,
      "highlight": null,
      "heat": 87,
      "tags": null,
      "images": [
        {
          "url": "https://azurecomcdn.azureedge.net/mediahandler/acomblog/media/Default/blog/4057c36f-d1b9-4580-9e5a-6c20fbe927ce.png",
          "width": 594,
          "height": 489,
          "title": null,
          "attribution": null,
          "isCached": true
        }
      ],
      "content": "\r\n",
      "type": "article",
      "ampWebUrl": null,
      "cdnAmpWebUrl": null,
      "publishedDateTime": "2021-07-29T01:30:35-07:00",
      "updatedDateTime": null,
      "provider": {
        "name": "Microsoft",
        "domain": "microsoft.com",
        "images": [
          {
            "url": "https://everyday-cc.github.io/azure/assets/images/organizations/microsoft.com-50x50.jpg",
            "width": 50,
            "height": 50,
            "title": null,
            "attribution": null,
            "isCached": false
          }
        ],
        "publishers": null,
        "authors": null
      },
      "locale": "en-us",
      "categories": [
        "news"
      ],
      "topics": [
        "Azure"
      ]
    },
    {
      "path": "_news/2021-07-28-microsofts-greatest-advantage-is-its-cloud-business-azure-bluebox.md",
      "title": "Microsoft's greatest advantage is its cloud business, Azure: Bluebox",
      "excerpt": "William de Gale, lead portfolio manager at BlueBox, discusses Microsoft's latest earnings. Got a confidential news tip? We want to hear from you. Sign up for free newsletters and get more CNBC delivered to your inbox Get this delivered to your inbox,",
      "sourceUrl": null,
      "webUrl": "https://www.cnbc.com/video/2021/07/28/microsofts-greatest-advantage-is-its-cloud-business-azure-bluebox.html",
      "originalUrl": "https://www.cnbc.com/video/2021/07/28/microsofts-greatest-advantage-is-its-cloud-business-azure-bluebox.html",
      "featuredContent": null,
      "highlight": null,
      "heat": 457,
      "tags": null,
      "images": [
        {
          "url": "https://image.cnbcfm.com/api/v1/image/106917937-16274675284ED4-SBEU-070821-WilliamdeGale.jpg?v=1627467527",
          "width": 1920,
          "height": 1080,
          "title": null,
          "attribution": null,
          "isCached": true
        }
      ],
      "content": "\r\n",
      "type": "article",
      "ampWebUrl": null,
      "cdnAmpWebUrl": null,
      "publishedDateTime": "2021-07-28T02:23:00-07:00",
      "updatedDateTime": null,
      "provider": {
        "name": "CNBC",
        "domain": "cnbc.com",
        "images": [
          {
            "url": "https://everyday-cc.github.io/azure/assets/images/organizations/cnbc.com-50x50.jpg",
            "width": 50,
            "height": 50,
            "title": null,
            "attribution": null,
            "isCached": false
          }
        ],
        "publishers": null,
        "authors": null
      },
      "locale": "en-us",
      "categories": [
        "news"
      ],
      "topics": [
        "Azure"
      ]
    },
    {
      "path": "_news/2021-07-27-general-availability-azure-stream-analytics-tools-for-visual-studio-code.md",
      "title": "General Availability: Azure Stream Analytics Tools for Visual Studio Code",
      "excerpt": "Azure Stream Analytics Tools for Visual Studio Code is for developers to easily author, test, debug, and manage Azure Stream Analytics jobs.",
      "sourceUrl": null,
      "webUrl": "https://azure.microsoft.com/en-us/updates/general-availability-azure-stream-analytics-tools-for-visual-studio-code/",
      "originalUrl": "https://azure.microsoft.com/en-us/updates/general-availability-azure-stream-analytics-tools-for-visual-studio-code/",
      "featuredContent": null,
      "highlight": null,
      "heat": 600,
      "tags": null,
      "images": null,
      "content": "\r\n",
      "type": "article",
      "ampWebUrl": null,
      "cdnAmpWebUrl": null,
      "publishedDateTime": "2021-07-27T09:00:05-07:00",
      "updatedDateTime": null,
      "provider": {
        "name": "Microsoft",
        "domain": "microsoft.com",
        "images": [
          {
            "url": "https://everyday-cc.github.io/azure/assets/images/organizations/microsoft.com-50x50.jpg",
            "width": 50,
            "height": 50,
            "title": null,
            "attribution": null,
            "isCached": false
          }
        ],
        "publishers": null,
        "authors": null
      },
      "locale": "en-us",
      "categories": [
        "news"
      ],
      "topics": [
        "Azure",
        "Analytics",
        "Developer tools"
      ]
    },
    {
      "path": "_news/2021-07-26-hcl-technologies-selected-as-a-strategic-launch-partner-for-microsoft-cloud-for-financial-services.md",
      "title": "HCL Technologies Selected As a Strategic Launch Partner For Microsoft Cloud For Financial Services",
      "excerpt": "Microsoft Cloud for Financial Services brings together capabilities with multilayered security and comprehensive compliance coverage to deliver differentiated customer experiences, improve employee collaboration and productivity,",
      "sourceUrl": null,
      "webUrl": "https://www.entrepreneur.com/article/378352",
      "originalUrl": "https://www.entrepreneur.com/article/378352",
      "featuredContent": null,
      "highlight": null,
      "heat": 208,
      "tags": null,
      "images": [
        {
          "url": "https://assets.entrepreneur.com/content/3x2/2000/1627292339-science-in-hd-ooNO0LlxZRM-unsplash.jpg?width=600&crop=16:9",
          "width": 600,
          "height": 338,
          "title": null,
          "attribution": null,
          "isCached": true
        }
      ],
      "content": "\r\n",
      "type": "article",
      "ampWebUrl": "https://www.entrepreneur.com/amphtml/378352",
      "cdnAmpWebUrl": "https://www-entrepreneur-com.cdn.ampproject.org/c/s/www.entrepreneur.com/amphtml/378352",
      "publishedDateTime": "2021-07-26T02:39:00-07:00",
      "updatedDateTime": null,
      "provider": {
        "name": "Entrepreneur",
        "domain": "entrepreneur.com",
        "images": [
          {
            "url": "https://everyday-cc.github.io/azure/assets/images/organizations/entrepreneur.com-50x50.jpg",
            "width": 50,
            "height": 50,
            "title": null,
            "attribution": null,
            "isCached": false
          }
        ],
        "publishers": null,
        "authors": null
      },
      "locale": "en-us",
      "categories": [
        "news"
      ],
      "topics": [
        "Azure"
      ]
    },
    {
      "path": "_news/2021-07-21-google-looker-gets-azure-support-api-explorer.md",
      "title": "Google Looker gets Azure support, API explorer",
      "excerpt": "As a part of Looker 21, the newest version of the Looker platform, Google launched new features including Microsoft Azure support.",
      "sourceUrl": null,
      "webUrl": "https://venturebeat.com/2021/07/21/google-looker-gets-azure-support-api-explorer/",
      "originalUrl": "https://venturebeat.com/2021/07/21/google-looker-gets-azure-support-api-explorer/",
      "featuredContent": null,
      "highlight": null,
      "heat": 97,
      "tags": null,
      "images": [
        {
          "url": "https://venturebeat.com/wp-content/uploads/2020/02/Looker-Life-1-21.jpg?w=1200&strip=all",
          "width": 1200,
          "height": 600,
          "title": null,
          "attribution": null,
          "isCached": true
        }
      ],
      "content": "\r\n",
      "type": "article",
      "ampWebUrl": "https://venturebeat.com/2021/07/21/google-looker-gets-azure-support-api-explorer/amp/",
      "cdnAmpWebUrl": "https://venturebeat-com.cdn.ampproject.org/c/s/venturebeat.com/2021/07/21/google-looker-gets-azure-support-api-explorer/amp/",
      "publishedDateTime": "2021-07-21T08:00:00-07:00",
      "updatedDateTime": null,
      "provider": {
        "name": "VentureBeat",
        "domain": "venturebeat.com",
        "images": [
          {
            "url": "https://everyday-cc.github.io/azure/assets/images/organizations/venturebeat.com-50x50.jpg",
            "width": 50,
            "height": 50,
            "title": null,
            "attribution": null,
            "isCached": false
          }
        ],
        "publishers": null,
        "authors": null
      },
      "locale": "en-us",
      "categories": [
        "news"
      ],
      "topics": [
        "Azure"
      ]
    },
    {
      "path": "_news/2021-07-19-private-preview-new-telemetry-for-sap-application-netweaver-in-azure-portal.md",
      "title": "Private preview: New telemetry for SAP Application (NetWeaver) in Azure portal",
      "excerpt": "SAP on Azure customers can now view SAP Application telemetry like short dumps, SDF/SMON and STO3 in Azure portal. \n",
      "sourceUrl": null,
      "webUrl": "https://azure.microsoft.com/en-us/updates/private-preview-new-telemetry-for-sap-application-netweaver-in-azure-portal/",
      "originalUrl": "https://azure.microsoft.com/en-us/updates/private-preview-new-telemetry-for-sap-application-netweaver-in-azure-portal/",
      "featuredContent": null,
      "highlight": null,
      "heat": 120,
      "tags": null,
      "images": null,
      "content": "\r\n",
      "type": "article",
      "ampWebUrl": null,
      "cdnAmpWebUrl": null,
      "publishedDateTime": "2021-07-19T08:00:02-07:00",
      "updatedDateTime": null,
      "provider": {
        "name": "Microsoft",
        "domain": "microsoft.com",
        "images": [
          {
            "url": "https://everyday-cc.github.io/azure/assets/images/organizations/microsoft.com-50x50.jpg",
            "width": 50,
            "height": 50,
            "title": null,
            "attribution": null,
            "isCached": false
          }
        ],
        "publishers": null,
        "authors": null
      },
      "locale": "en-us",
      "categories": [
        "news"
      ],
      "topics": [
        "Azure",
        "Management tools"
      ]
    },
    {
      "path": "_news/2021-07-19-how-cloud-computing-can-improve-5g-wireless-networks.md",
      "title": "How cloud computing can improve 5G wireless networks",
      "excerpt": "A great deal has been written about the technologies fueling 5G, especially how those technologies will improve the experience that users have regarding connectivity. Similarly, much has been said about how ongoing developments in technology will usher in a new generation of network-aware applications.",
      "sourceUrl": null,
      "webUrl": "https://azure.microsoft.com/blog/how-cloud-computing-can-improve-5g-wireless-networks/",
      "originalUrl": "https://azure.microsoft.com/blog/how-cloud-computing-can-improve-5g-wireless-networks/",
      "featuredContent": null,
      "highlight": null,
      "heat": 72,
      "tags": null,
      "images": [
        {
          "url": "https://azurecomcdn.azureedge.net/mediahandler/acomblog/media/Default/blog/e9de9512-0b20-4fb5-8d7f-a3777e28438d.png",
          "width": 1430,
          "height": 771,
          "title": null,
          "attribution": null,
          "isCached": true
        }
      ],
      "content": "\r\n",
      "type": "article",
      "ampWebUrl": null,
      "cdnAmpWebUrl": null,
      "publishedDateTime": "2021-07-19T01:00:02-07:00",
      "updatedDateTime": null,
      "provider": {
        "name": "Microsoft",
        "domain": "microsoft.com",
        "images": [
          {
            "url": "https://everyday-cc.github.io/azure/assets/images/organizations/microsoft.com-50x50.jpg",
            "width": 50,
            "height": 50,
            "title": null,
            "attribution": null,
            "isCached": false
          }
        ],
        "publishers": null,
        "authors": null
      },
      "locale": "en-us",
      "categories": [
        "news"
      ],
      "topics": [
        "Azure"
      ]
    },
    {
      "path": "_news/2021-07-19-next-generation-firewall-capabilities-with-azure-firewall-premium.md",
      "title": "Next-generation firewall capabilities with Azure Firewall Premium",
      "excerpt": "Following the preview release announced in February 2021, we are announcing the general availability release of Azure Firewall Premium. Key features in this release include: TLS Inspection, IDPS, Web Categories, and URL Filtering.",
      "sourceUrl": null,
      "webUrl": "https://azure.microsoft.com/blog/nextgeneration-firewall-capabilities-with-azure-firewall-premium/",
      "originalUrl": "https://azure.microsoft.com/blog/nextgeneration-firewall-capabilities-with-azure-firewall-premium/",
      "featuredContent": null,
      "highlight": null,
      "heat": 109,
      "tags": null,
      "images": [
        {
          "url": "https://azurecomcdn.azureedge.net/mediahandler/acomblog/media/Default/blog/6a0956b5-eb59-4661-8810-46bd5214e3f9.png",
          "width": 862,
          "height": 768,
          "title": null,
          "attribution": null,
          "isCached": true
        }
      ],
      "content": "\r\n",
      "type": "article",
      "ampWebUrl": null,
      "cdnAmpWebUrl": null,
      "publishedDateTime": "2021-07-19T00:00:01-07:00",
      "updatedDateTime": null,
      "provider": {
        "name": "Microsoft",
        "domain": "microsoft.com",
        "images": [
          {
            "url": "https://everyday-cc.github.io/azure/assets/images/organizations/microsoft.com-50x50.jpg",
            "width": 50,
            "height": 50,
            "title": null,
            "attribution": null,
            "isCached": false
          }
        ],
        "publishers": null,
        "authors": null
      },
      "locale": "en-us",
      "categories": [
        "news"
      ],
      "topics": [
        "Azure",
        "Networking"
      ]
    },
    {
      "path": "_news/2021-07-16-azure-automation-support-for-user-assigned-managed-identities-is-now-in-public-preview.md",
      "title": "Azure Automation support for User Assigned Managed Identities is now in public preview",
      "excerpt": "Use user-assigned identities for Azure Automation runbook jobs. ",
      "sourceUrl": null,
      "webUrl": "https://azure.microsoft.com/en-us/updates/azure-automation-user-assigned-identities/",
      "originalUrl": "https://azure.microsoft.com/en-us/updates/azure-automation-user-assigned-identities/",
      "featuredContent": null,
      "highlight": null,
      "heat": 79,
      "tags": null,
      "images": null,
      "content": "\r\n",
      "type": "article",
      "ampWebUrl": null,
      "cdnAmpWebUrl": null,
      "publishedDateTime": "2021-07-16T09:00:00-07:00",
      "updatedDateTime": null,
      "provider": {
        "name": "Microsoft",
        "domain": "microsoft.com",
        "images": [
          {
            "url": "https://everyday-cc.github.io/azure/assets/images/organizations/microsoft.com-50x50.jpg",
            "width": 50,
            "height": 50,
            "title": null,
            "attribution": null,
            "isCached": false
          }
        ],
        "publishers": null,
        "authors": null
      },
      "locale": "en-us",
      "categories": [
        "news"
      ],
      "topics": [
        "Azure"
      ]
    },
    {
      "path": "_news/2021-07-14-limited-preview-migrate-your-azure-data-lake-storage-from-gen1-to-gen2-using-the-azure-portal.md",
      "title": "Limited preview: Migrate your Azure Data Lake Storage from Gen1 to Gen2 using the Azure Portal",
      "excerpt": "Use this simple experience to migrate your data from Azure Data Lake Storage Gen1 to Gen2 to speed up your time to insights.",
      "sourceUrl": null,
      "webUrl": "https://azure.microsoft.com/en-us/updates/limited-preview-migrate-your-azure-data-lake-storage-from-gen1-to-gen2-using-the-azure-portal/",
      "originalUrl": "https://azure.microsoft.com/en-us/updates/limited-preview-migrate-your-azure-data-lake-storage-from-gen1-to-gen2-using-the-azure-portal/",
      "featuredContent": null,
      "highlight": null,
      "heat": 109,
      "tags": null,
      "images": null,
      "content": "\r\n",
      "type": "article",
      "ampWebUrl": null,
      "cdnAmpWebUrl": null,
      "publishedDateTime": "2021-07-14T15:16:38-07:00",
      "updatedDateTime": null,
      "provider": {
        "name": "Microsoft",
        "domain": "microsoft.com",
        "images": [
          {
            "url": "https://everyday-cc.github.io/azure/assets/images/organizations/microsoft.com-50x50.jpg",
            "width": 50,
            "height": 50,
            "title": null,
            "attribution": null,
            "isCached": false
          }
        ],
        "publishers": null,
        "authors": null
      },
      "locale": "en-us",
      "categories": [
        "news"
      ],
      "topics": [
        "Azure",
        "Storage",
        "Management tools"
      ]
    },
    {
      "path": "_news/2021-07-14-free-extended-security-updates-only-on-azure-for-windows-server-2012-r2and-sql-server-2012.md",
      "title": "Free Extended Security Updates only on Azure for Windows Server 2012 /R2and SQL Server 2012 ",
      "excerpt": "Learn how you can take advantage of free Extended Security only Azure for workloads running on Windows Server 2012/R2 and SQL Server 2012 releases. ",
      "sourceUrl": null,
      "webUrl": "https://azure.microsoft.com/en-us/updates/free-extended-security-updates-only-on-azure-for-windows-server-2012-r2and-sql-server-2012/",
      "originalUrl": "https://azure.microsoft.com/en-us/updates/free-extended-security-updates-only-on-azure-for-windows-server-2012-r2and-sql-server-2012/",
      "featuredContent": null,
      "highlight": null,
      "heat": 93,
      "tags": null,
      "images": null,
      "content": "\r\n",
      "type": "article",
      "ampWebUrl": null,
      "cdnAmpWebUrl": null,
      "publishedDateTime": "2021-07-14T09:00:34-07:00",
      "updatedDateTime": null,
      "provider": {
        "name": "Microsoft",
        "domain": "microsoft.com",
        "images": [
          {
            "url": "https://everyday-cc.github.io/azure/assets/images/organizations/microsoft.com-50x50.jpg",
            "width": 50,
            "height": 50,
            "title": null,
            "attribution": null,
            "isCached": false
          }
        ],
        "publishers": null,
        "authors": null
      },
      "locale": "en-us",
      "categories": [
        "news"
      ],
      "topics": [
        "Azure",
        "Security"
      ]
    },
    {
      "path": "_news/2021-07-14-azure-machine-learning-public-preview-announcements-july-2021.md",
      "title": "Azure Machine Learning public preview announcements July 2021",
      "excerpt": "New features Custom Containers in Managed Online Endpoints and Job Creation UI are now available in preview in Azure Machine Learning.",
      "sourceUrl": null,
      "webUrl": "https://azure.microsoft.com/en-us/updates/azure-machine-learning-public-preview-announcements-july-2021/",
      "originalUrl": "https://azure.microsoft.com/en-us/updates/azure-machine-learning-public-preview-announcements-july-2021/",
      "featuredContent": null,
      "highlight": null,
      "heat": 84,
      "tags": null,
      "images": null,
      "content": "\r\n",
      "type": "article",
      "ampWebUrl": null,
      "cdnAmpWebUrl": null,
      "publishedDateTime": "2021-07-14T09:00:32-07:00",
      "updatedDateTime": null,
      "provider": {
        "name": "Microsoft",
        "domain": "microsoft.com",
        "images": [
          {
            "url": "https://everyday-cc.github.io/azure/assets/images/organizations/microsoft.com-50x50.jpg",
            "width": 50,
            "height": 50,
            "title": null,
            "attribution": null,
            "isCached": false
          }
        ],
        "publishers": null,
        "authors": null
      },
      "locale": "en-us",
      "categories": [
        "news"
      ],
      "topics": [
        "Azure",
        "AI"
      ]
    },
    {
      "path": "_news/2021-07-14-confidential-computing-using-always-encrypted-with-secure-enclaves-for-azure-sql-database-in-general-availability.md",
      "title": "Confidential computing using Always Encrypted with secure enclaves for Azure SQL Database in general availability",
      "excerpt": "Always Encrypted with secure enclaves helps prevent malicious admins and malware from exfiltrating sensitive data, while enabling in-place encryption and rich confidential computations, including pattern matching, range comparisons, and sorting.",
      "sourceUrl": null,
      "webUrl": "https://azure.microsoft.com/en-us/updates/confidential-computing-using-always-encrypted-with-secure-enclaves-for-azure-sql-database-in-general-availability/",
      "originalUrl": "https://azure.microsoft.com/en-us/updates/confidential-computing-using-always-encrypted-with-secure-enclaves-for-azure-sql-database-in-general-availability/",
      "featuredContent": null,
      "highlight": null,
      "heat": 113,
      "tags": null,
      "images": null,
      "content": "\r\n",
      "type": "article",
      "ampWebUrl": null,
      "cdnAmpWebUrl": null,
      "publishedDateTime": "2021-07-14T09:00:32-07:00",
      "updatedDateTime": null,
      "provider": {
        "name": "Microsoft",
        "domain": "microsoft.com",
        "images": [
          {
            "url": "https://everyday-cc.github.io/azure/assets/images/organizations/microsoft.com-50x50.jpg",
            "width": 50,
            "height": 50,
            "title": null,
            "attribution": null,
            "isCached": false
          }
        ],
        "publishers": null,
        "authors": null
      },
      "locale": "en-us",
      "categories": [
        "news"
      ],
      "topics": [
        "Azure",
        "Databases"
      ]
    },
    {
      "path": "_news/2021-07-14-drive-growth-with-the-most-partner-focused-business-platform.md",
      "title": "Drive growth with the most partner-focused business platform",
      "excerpt": "The Microsoft Cloud opportunity is stronger than ever with over 95 percent of Fortune 500 companies using Azure, over 145 million daily active users on Microsoft Teams, and over 250,000 organizations using Microsoft Dynamics 365 and Microsoft Power Platform to run and transform their businesses—partners",
      "sourceUrl": null,
      "webUrl": "https://azure.microsoft.com/blog/drive-growth-with-the-most-partnerfocused-business-platform/",
      "originalUrl": "https://azure.microsoft.com/blog/drive-growth-with-the-most-partnerfocused-business-platform/",
      "featuredContent": null,
      "highlight": null,
      "heat": 72,
      "tags": null,
      "images": [
        {
          "url": "https://azurecomcdn.azureedge.net/mediahandler/acomblog/media/Default/blog/efb5835a-8a44-49f4-b70d-363783e698b7.png",
          "width": 960,
          "height": 600,
          "title": null,
          "attribution": null,
          "isCached": true
        }
      ],
      "content": "\r\n",
      "type": "article",
      "ampWebUrl": null,
      "cdnAmpWebUrl": null,
      "publishedDateTime": "2021-07-14T01:00:29-07:00",
      "updatedDateTime": null,
      "provider": {
        "name": "Microsoft",
        "domain": "microsoft.com",
        "images": [
          {
            "url": "https://everyday-cc.github.io/azure/assets/images/organizations/microsoft.com-50x50.jpg",
            "width": 50,
            "height": 50,
            "title": null,
            "attribution": null,
            "isCached": false
          }
        ],
        "publishers": null,
        "authors": null
      },
      "locale": "en-us",
      "categories": [
        "news"
      ],
      "topics": [
        "Azure"
      ]
    },
    {
      "path": "_news/2021-07-14-innovate-from-cloud-to-edge-on-your-terms-with-azure.md",
      "title": "Innovate from cloud to edge on your terms with Azure",
      "excerpt": "The challenges of the past year revealed that serving and making a difference for each other, our communities, and the world around us is more critical than ever. In order to persevere and drive business success, organizations must be future-ready, build on their terms, operate hybrid seamlessly, and",
      "sourceUrl": null,
      "webUrl": "https://azure.microsoft.com/blog/innovate-from-cloud-to-edge-on-your-terms-with-azure/",
      "originalUrl": "https://azure.microsoft.com/blog/innovate-from-cloud-to-edge-on-your-terms-with-azure/",
      "featuredContent": null,
      "highlight": null,
      "heat": 131,
      "tags": null,
      "images": [
        {
          "url": "https://azurecomcdn.azureedge.net/mediahandler/acomblog/media/Default/blog/7d530ede-a64e-4282-b82d-a8657faa18ed.png",
          "width": 1024,
          "height": 427,
          "title": null,
          "attribution": null,
          "isCached": true
        }
      ],
      "content": "\r\n",
      "type": "article",
      "ampWebUrl": null,
      "cdnAmpWebUrl": null,
      "publishedDateTime": "2021-07-14T01:00:29-07:00",
      "updatedDateTime": null,
      "provider": {
        "name": "Microsoft",
        "domain": "microsoft.com",
        "images": [
          {
            "url": "https://everyday-cc.github.io/azure/assets/images/organizations/microsoft.com-50x50.jpg",
            "width": 50,
            "height": 50,
            "title": null,
            "attribution": null,
            "isCached": false
          }
        ],
        "publishers": null,
        "authors": null
      },
      "locale": "en-us",
      "categories": [
        "news"
      ],
      "topics": [
        "Azure",
        "AI",
        "Management tools"
      ]
    },
    {
      "path": "_news/2021-07-13-manage-rdp-and-ssh-connectivity-at-scale-with-azure-bastion.md",
      "title": "Manage RDP and SSH connectivity at scale with Azure Bastion",
      "excerpt": "Security is at the forefront of user and administrator connectivity to cloud services. As enterprises continue to move mission-critical applications to the Cloud, the need for secure, scalable, and reliable remote public connectivity and jumpbox services increases.",
      "sourceUrl": null,
      "webUrl": "https://azure.microsoft.com/blog/manage-rdp-and-ssh-connectivity-at-scale-with-azure-bastion/",
      "originalUrl": "https://azure.microsoft.com/blog/manage-rdp-and-ssh-connectivity-at-scale-with-azure-bastion/",
      "featuredContent": null,
      "highlight": null,
      "heat": 91,
      "tags": null,
      "images": [
        {
          "url": "https://azurecomcdn.azureedge.net/mediahandler/acomblog/media/Default/blog/a380e21f-b1a6-457b-94c5-1fd1b800db63.png",
          "width": 1024,
          "height": 565,
          "title": null,
          "attribution": null,
          "isCached": true
        }
      ],
      "content": "\r\n",
      "type": "article",
      "ampWebUrl": null,
      "cdnAmpWebUrl": null,
      "publishedDateTime": "2021-07-13T04:00:17-07:00",
      "updatedDateTime": null,
      "provider": {
        "name": "Microsoft",
        "domain": "microsoft.com",
        "images": [
          {
            "url": "https://everyday-cc.github.io/azure/assets/images/organizations/microsoft.com-50x50.jpg",
            "width": 50,
            "height": 50,
            "title": null,
            "attribution": null,
            "isCached": false
          }
        ],
        "publishers": null,
        "authors": null
      },
      "locale": "en-us",
      "categories": [
        "news"
      ],
      "topics": [
        "Azure",
        "Security",
        "Networking"
      ]
    },
    {
      "path": "_news/2021-07-13-deliver-scalable-cost-effective-disk-storage-for-azure-vmware-solution.md",
      "title": "Deliver scalable, cost-effective Disk Storage for Azure VMware Solution",
      "excerpt": "Today, we are announcing the preview of disk pool enabling Azure Disk Storage as a persistent storage option for Azure VMware Solution. With this announcement, you can gain flexibility for your data needs with scalable and cost-effective cloud storage for VMware workloads running on Azure.",
      "sourceUrl": null,
      "webUrl": "https://azure.microsoft.com/blog/deliver-scalable-costeffective-disk-storage-for-azure-vmware-solution/",
      "originalUrl": "https://azure.microsoft.com/blog/deliver-scalable-costeffective-disk-storage-for-azure-vmware-solution/",
      "featuredContent": null,
      "highlight": null,
      "heat": 189,
      "tags": null,
      "images": null,
      "content": "\r\n",
      "type": "article",
      "ampWebUrl": null,
      "cdnAmpWebUrl": null,
      "publishedDateTime": "2021-07-13T02:00:16-07:00",
      "updatedDateTime": null,
      "provider": {
        "name": "Microsoft",
        "domain": "microsoft.com",
        "images": [
          {
            "url": "https://everyday-cc.github.io/azure/assets/images/organizations/microsoft.com-50x50.jpg",
            "width": 50,
            "height": 50,
            "title": null,
            "attribution": null,
            "isCached": false
          }
        ],
        "publishers": null,
        "authors": null
      },
      "locale": "en-us",
      "categories": [
        "news"
      ],
      "topics": [
        "Azure",
        "Storage",
        "Management tools",
        "Compute"
      ]
    },
    {
      "path": "_news/2021-07-12-general-availability-azure-api-management-updates-july-2021.md",
      "title": "General availability: Azure API Management updates - July 2021",
      "excerpt": "Azure API Management service has been updated to provide better support to customers through policy expressions and Power platform.",
      "sourceUrl": null,
      "webUrl": "https://azure.microsoft.com/en-us/updates/azure-api-management-updates-july-2021/",
      "originalUrl": "https://azure.microsoft.com/en-us/updates/azure-api-management-updates-july-2021/",
      "featuredContent": null,
      "highlight": null,
      "heat": 584,
      "tags": null,
      "images": [
        {
          "url": "https://azurecomcdn.azureedge.net/mediahandler/acomblog/updates/UpdatesV2/blog/77ca2356-075a-4e23-98b8-e1193664c8ed.png",
          "width": 1055,
          "height": 434,
          "title": null,
          "attribution": null,
          "isCached": true
        }
      ],
      "content": "\r\n",
      "type": "article",
      "ampWebUrl": null,
      "cdnAmpWebUrl": null,
      "publishedDateTime": "2021-07-12T12:55:36-07:00",
      "updatedDateTime": null,
      "provider": {
        "name": "Microsoft",
        "domain": "microsoft.com",
        "images": [
          {
            "url": "https://everyday-cc.github.io/azure/assets/images/organizations/microsoft.com-50x50.jpg",
            "width": 50,
            "height": 50,
            "title": null,
            "attribution": null,
            "isCached": false
          }
        ],
        "publishers": null,
        "authors": null
      },
      "locale": "en-us",
      "categories": [
        "news"
      ],
      "topics": [
        "Azure",
        "Integration"
      ]
    },
    {
      "path": "_news/2021-07-12-advancing-application-reliability-with-the-azure-well-architected-framework.md",
      "title": "Advancing application reliability with the Azure Well-Architected Framework",
      "excerpt": "We created the Azure Well-Architected Framework to help improve the quality of your workloads, and reliability is one of its five core pillars so for the latest post in our series, I have asked Cloud Advocate David Blank-Edelman to run through how best to approach using the framework to guide your conversations and",
      "sourceUrl": null,
      "webUrl": "https://azure.microsoft.com/blog/advancing-application-reliability-with-the-azure-wellarchitected-framework/",
      "originalUrl": "https://azure.microsoft.com/blog/advancing-application-reliability-with-the-azure-wellarchitected-framework/",
      "featuredContent": null,
      "highlight": null,
      "heat": 87,
      "tags": null,
      "images": [
        {
          "url": "https://azurecomcdn.azureedge.net/mediahandler/acomblog/media/Default/blog/e8d37bf3-6588-40a9-8462-cf1eae99c496.png",
          "width": 967,
          "height": 1121,
          "title": null,
          "attribution": null,
          "isCached": true
        }
      ],
      "content": "\r\n",
      "type": "article",
      "ampWebUrl": null,
      "cdnAmpWebUrl": null,
      "publishedDateTime": "2021-07-12T02:00:02-07:00",
      "updatedDateTime": null,
      "provider": {
        "name": "Microsoft",
        "domain": "microsoft.com",
        "images": [
          {
            "url": "https://everyday-cc.github.io/azure/assets/images/organizations/microsoft.com-50x50.jpg",
            "width": 50,
            "height": 50,
            "title": null,
            "attribution": null,
            "isCached": false
          }
        ],
        "publishers": null,
        "authors": null
      },
      "locale": "en-us",
      "categories": [
        "news"
      ],
      "topics": [
        "Azure",
        "Security"
      ]
    },
    {
      "path": "_news/2021-07-09-insight-wins-2021-microsoft-worldwide-partner-of-the-year-awards-for-azure-migration-and-solution-assessments.md",
      "title": "Insight Wins 2021 Microsoft Worldwide Partner of the Year Awards for Azure Migration and Solution Assessments",
      "excerpt": "Insight Enterprises (NASDAQ:NSIT), the global provider of Insight Intelligent Technology Solutions™ for organizations of all sizes, today announced it",
      "sourceUrl": null,
      "webUrl": "https://www.marketwatch.com/press-release/insight-wins-2021-microsoft-worldwide-partner-of-the-year-awards-for-azure-migration-and-solution-assessments-2021-07-09",
      "originalUrl": "https://www.marketwatch.com/press-release/insight-wins-2021-microsoft-worldwide-partner-of-the-year-awards-for-azure-migration-and-solution-assessments-2021-07-09",
      "featuredContent": null,
      "highlight": null,
      "heat": 315,
      "tags": null,
      "images": [
        {
          "url": "https://mw3.wsj.net/mw5/content/logos/mw_logo_social.png",
          "width": 1200,
          "height": 630,
          "title": null,
          "attribution": null,
          "isCached": true
        }
      ],
      "content": "\r\n",
      "type": "article",
      "ampWebUrl": null,
      "cdnAmpWebUrl": null,
      "publishedDateTime": "2021-07-09T09:02:00-07:00",
      "updatedDateTime": null,
      "provider": {
        "name": "MarketWatch",
        "domain": "marketwatch.com",
        "images": [
          {
            "url": "https://everyday-cc.github.io/azure/assets/images/organizations/marketwatch.com-50x50.jpg",
            "width": 50,
            "height": 50,
            "title": null,
            "attribution": null,
            "isCached": false
          }
        ],
        "publishers": null,
        "authors": null
      },
      "locale": "en-us",
      "categories": [
        "news"
      ],
      "topics": [
        "Azure",
        "Migration"
      ]
    }
  ],
  "nextPage": 2
}